Metadata-Version: 2.1
Name: countrywrangler
Version: 0.2.7
Summary: A library that simplifies the handling of country-related data. Easily standardize your data according to ISO 3166-1 and make it consistent across your project.
Home-page: https://github.com/TheHenryWills/CountryWrangler
Download-URL: https://github.com/TheHenryWills/CountryWrangler/archive/refs/tags/v_0.2.7.tar.gz
Author: Henry Wills
Author-email: hello@henrywills.com
License: MIT
Project-URL: Documentation, https://countrywrangler.readthedocs.io/en/latest/
Project-URL: Linktree, https://linktr.ee/thehenrywills
Keywords: iso-3166,iso-3166-1 ,normalize, countries-data,country,data-normalization,data-cleaning
Classifier: Development Status :: 5 - Production/Stable
Classifier: Intended Audience :: Developers
Classifier: Topic :: Software Development :: Build Tools
Classifier: License :: OSI Approved :: MIT License
Classifier: Programming Language :: Python :: 3
Classifier: Programming Language :: Python :: 3.4
Classifier: Programming Language :: Python :: 3.5
Classifier: Programming Language :: Python :: 3.6
Classifier: Programming Language :: Python :: 3.7
Classifier: Programming Language :: Python :: 3.8
Classifier: Programming Language :: Python :: 3.9
License-File: LICENSE
